README
setup.py
chatter/__init__.py
chatter/base.py
chatter.egg-info/PKG-INFO
chatter.egg-info/SOURCES.txt
chatter.egg-info/dependency_links.txt
chatter.egg-info/requires.txt
chatter.egg-info/top_level.txt
chatter.egg-info/zip-safe