Metadata-Version: 1.0
Name: chatter
Version: 0.1.3
Summary: ('The minimalist yet fully featured Chatter API class, heavily inspired by Python Twitter Tools.',)
Home-page: https://github.com/nixmc/chatter
Author: Steve Winton
Author-email: steve.winton@nixonmcinnes.co.uk
License: MIT
Keywords: chatter api salesforce
Platform: UNKNOWN
Classifier: Development Status :: 4 - Beta
Classifier: Topic :: Utilities
Classifier: Topic :: Internet :: WWW/HTTP :: Dynamic Content :: CGI Tools/Libraries
Classifier: Operating System :: OS Independent
Classifier: Programming Language :: Python :: 2.6
Classifier: Programming Language :: Python :: 2.7
Classifier: License :: OSI Approved :: MIT License
